{
  "unversionedId": "Core/SetVariable",
  "id": "version-v0.17.0/Core/SetVariable",
  "title": "SetVariable Step | Core SDK Documentation",
  "description": "Sets the value of a named variable.. Use this step to easily automate forensic and e-discovery workflows using Sequence.",
  "source": "@site/steps_versioned_docs/version-v0.17.0/Core/SetVariable.md",
  "sourceDirName": "Core",
  "slug": "/Core/SetVariable",
  "permalink": "/steps/v0.17.0/Core/SetVariable",
  "draft": false,
  "editUrl": "https://gitlab.com/sequence/sequence-docs/edit/main/steps_versioned_docs/version-v0.17.0/Core/SetVariable.md",
  "tags": [
    {
      "label": "Step",
      "permalink": "/steps/v0.17.0/tags/step"
    },
    {
      "label": "Core",
      "permalink": "/steps/v0.17.0/tags/core"
    }
  ],
  "version": "v0.17.0",
  "frontMatter": {
    "title": "SetVariable Step | Core SDK Documentation",
    "sidebar_label": "SetVariable",
    "description": "Sets the value of a named variable.. Use this step to easily automate forensic and e-discovery workflows using Sequence.",
    "tags": [
      "Step",
      "Core"
    ],
    "hide_title": true,
    "hide_table_of_contents": true
  },
  "sidebar": "steps",
  "previous": {
    "title": "Sequence",
    "permalink": "/steps/v0.17.0/Core/Sequence"
  },
  "next": {
    "title": "StandardErrorWrite",
    "permalink": "/steps/v0.17.0/Core/StandardErrorWrite"
  }
}