{
  "unversionedId": "Core/EntityHasProperty",
  "id": "version-v0.16.0/Core/EntityHasProperty",
  "title": "EntityHasProperty Step | Core SDK Documentation",
  "description": "Checks if an entity has a particular property.. Use this step to easily automate forensic and e-discovery workflows using Sequence.",
  "source": "@site/steps_versioned_docs/version-v0.16.0/Core/EntityHasProperty.md",
  "sourceDirName": "Core",
  "slug": "/Core/EntityHasProperty",
  "permalink": "/steps/v0.16.0/Core/EntityHasProperty",
  "draft": false,
  "editUrl": "https://gitlab.com/sequence/sequence-docs/edit/main/steps_versioned_docs/version-v0.16.0/Core/EntityHasProperty.md",
  "tags": [
    {
      "label": "Step",
      "permalink": "/steps/v0.16.0/tags/step"
    },
    {
      "label": "Core",
      "permalink": "/steps/v0.16.0/tags/core"
    }
  ],
  "version": "v0.16.0",
  "frontMatter": {
    "title": "EntityHasProperty Step | Core SDK Documentation",
    "sidebar_label": "EntityHasProperty",
    "description": "Checks if an entity has a particular property.. Use this step to easily automate forensic and e-discovery workflows using Sequence.",
    "tags": [
      "Step",
      "Core"
    ],
    "hide_title": true,
    "hide_table_of_contents": true
  },
  "sidebar": "steps",
  "previous": {
    "title": "EntityGetValue",
    "permalink": "/steps/v0.16.0/Core/EntityGetValue"
  },
  "next": {
    "title": "EntityMapProperties",
    "permalink": "/steps/v0.16.0/Core/EntityMapProperties"
  }
}