{
  "unversionedId": "Core/ArrayLength",
  "id": "version-v0.18.0/Core/ArrayLength",
  "title": "ArrayLength Step | Core SDK Documentation",
  "description": "Counts the elements in an array or entities in an entity stream.. Use this step to easily automate forensic and e-discovery workflows using Phoenix.",
  "source": "@site/steps_versioned_docs/version-v0.18.0/Core/ArrayLength.md",
  "sourceDirName": "Core",
  "slug": "/Core/ArrayLength",
  "permalink": "/steps/Core/ArrayLength",
  "draft": false,
  "editUrl": "https://gitlab.com/Phoenix/Phoenix-docs/edit/main/steps_versioned_docs/version-v0.18.0/Core/ArrayLength.md",
  "tags": [
    {
      "label": "Step",
      "permalink": "/steps/tags/step"
    },
    {
      "label": "Core",
      "permalink": "/steps/tags/core"
    }
  ],
  "version": "v0.18.0",
  "frontMatter": {
    "title": "ArrayLength Step | Core SDK Documentation",
    "sidebar_label": "ArrayLength",
    "description": "Counts the elements in an array or entities in an entity stream.. Use this step to easily automate forensic and e-discovery workflows using Phoenix.",
    "tags": [
      "Step",
      "Core"
    ],
    "hide_title": true,
    "hide_table_of_contents": true
  },
  "sidebar": "steps",
  "previous": {
    "title": "ArrayLast",
    "permalink": "/steps/Core/ArrayLast"
  },
  "next": {
    "title": "ArrayMap",
    "permalink": "/steps/Core/ArrayMap"
  }
}