{
  "unversionedId": "Enums/AutopsyCaseType",
  "id": "version-v0.18.0/Enums/AutopsyCaseType",
  "title": "AutopsyCaseType | Enums",
  "description": ". Use this step to easily automate forensic and e-discovery workflows using Sequence.",
  "source": "@site/steps_versioned_docs/version-v0.18.0/Enums/AutopsyCaseType.md",
  "sourceDirName": "Enums",
  "slug": "/Enums/AutopsyCaseType",
  "permalink": "/steps/Enums/AutopsyCaseType",
  "draft": false,
  "editUrl": "https://gitlab.com/sequence/sequence-docs/edit/main/steps_versioned_docs/version-v0.18.0/Enums/AutopsyCaseType.md",
  "tags": [
    {
      "label": "Enums",
      "permalink": "/steps/tags/enums"
    },
    {
      "label": "Unit",
      "permalink": "/steps/tags/unit"
    }
  ],
  "version": "v0.18.0",
  "frontMatter": {
    "title": "AutopsyCaseType | Enums",
    "sidebar_label": "AutopsyCaseType",
    "description": ". Use this step to easily automate forensic and e-discovery workflows using Sequence.",
    "tags": [
      "Enums",
      "Unit"
    ],
    "hide_title": true,
    "hide_table_of_contents": true
  },
  "sidebar": "steps",
  "previous": {
    "title": "ArtifactType",
    "permalink": "/steps/Enums/ArtifactType"
  },
  "next": {
    "title": "DeduplicateBy",
    "permalink": "/steps/Enums/DeduplicateBy"
  }
}